svg_pltmarker/__init__.py
svg_pltmarker/path_converter.py
svg_pltmarker/svg_module/__init__.py
svg_pltmarker/svg_module/svg_circle.py
svg_pltmarker/svg_module/svg_ellipse.py
svg_pltmarker/svg_module/svg_graphic_element_base.py
svg_pltmarker/svg_module/svg_line.py
svg_pltmarker/svg_module/svg_object.py
svg_pltmarker/svg_module/svg_path.py
svg_pltmarker/svg_module/svg_polygon.py
svg_pltmarker/svg_module/svg_polyline.py
svg_pltmarker/svg_module/svg_rect.py
svg_pltmarker-1.0.0.dist-info/METADATA
svg_pltmarker-1.0.0.dist-info/WHEEL
svg_pltmarker-1.0.0.dist-info/licenses/LICENSE
svg_pltmarker-1.0.0.dist-info/RECORD
