Metadata-Version: 2.1
Name: svg_pltmarker
Version: 1.0.0
Summary: A library for generating Matplotlib markers from SVG files.
Project-URL: repository, https://github.com/Yuki-Imajuku/SVG-pltmarker
Author-email: Yuki Imajuku <yuki.imjk@gmail.com>
License: MIT License
License-File: LICENSE
Keywords: SVG,graphic,marker,matplotlib,path
Classifier: Development Status :: 5 - Production/Stable
Classifier: License :: OSI Approved :: MIT License
Classifier: Operating System :: OS Independent
Classifier: Programming Language :: Python
Classifier: Programming Language :: Python :: 3
Classifier: Programming Language :: Python :: 3 :: Only
Classifier: Programming Language :: Python :: 3.10
Classifier: Programming Language :: Python :: 3.11
Classifier: Programming Language :: Python :: 3.12
Classifier: Topic :: Multimedia :: Graphics
Classifier: Topic :: Scientific/Engineering :: Visualization
Classifier: Topic :: Software Development :: Libraries :: Python Modules
Requires-Python: >=3.10
Requires-Dist: matplotlib>=3.6.0
Requires-Dist: numpy>=1.22.0
Requires-Dist: pydantic>=2.0.0
Provides-Extra: dev
Requires-Dist: black~=24.2.0; extra == 'dev'
Requires-Dist: flake8~=7.0.0; extra == 'dev'
Requires-Dist: isort~=5.13.2; extra == 'dev'
Requires-Dist: mypy~=1.8.0; extra == 'dev'
Requires-Dist: pytest~=8.0.1; extra == 'dev'
